mantichora/__init__.py
mantichora/_version.py
mantichora/hubmp.py
mantichora/hubthreading.py
mantichora/main.py
mantichora-0.12.0.dist-info/LICENSE
mantichora-0.12.0.dist-info/METADATA
mantichora-0.12.0.dist-info/WHEEL
mantichora-0.12.0.dist-info/top_level.txt
mantichora-0.12.0.dist-info/RECORD
