Metadata-Version: 2.1
Name: mantichora
Version: 0.12.0
Summary: A simple interface to multiprocessing and threading
Home-page: https://github.com/alphatwirl/mantichora
Author: Tai Sakuma
Author-email: tai.sakuma@gmail.com
License: UNKNOWN
Platform: UNKNOWN
Classifier: Development Status :: 4 - Beta
Classifier: Intended Audience :: Developers
Classifier: Intended Audience :: End Users/Desktop
Classifier: License :: OSI Approved :: BSD License
Classifier: Programming Language :: Python :: 3.6
Classifier: Programming Language :: Python :: 3.7
Classifier: Programming Language :: Python :: 3.8
Classifier: Programming Language :: Python :: 3.9
Requires-Dist: atpbar (>=1.0.8)
Provides-Extra: tests
Requires-Dist: pytest (>=5.4) ; extra == 'tests'
Requires-Dist: pytest-cov (>=2.8) ; extra == 'tests'
Requires-Dist: pytest-console-scripts (>=0.2) ; extra == 'tests'
